soral_data_test/__init__.py
soral_data_test/data.py
soral_data_test-0.0.4.dist-info/LICENSE.txt
soral_data_test-0.0.4.dist-info/METADATA
soral_data_test-0.0.4.dist-info/WHEEL
soral_data_test-0.0.4.dist-info/top_level.txt
soral_data_test-0.0.4.dist-info/RECORD
