Metadata-Version: 2.1
Name: soral-data-test
Version: 0.0.4
Summary: X-I-A
Home-page: https://develop.x-i-a.com/docs/soral-data-test/0.0.4/index.html
Author: X-I-A
Author-email: admin@x-i-a.com
License: UNKNOWN
Platform: UNKNOWN
Requires-Python: >=3.9
License-File: LICENSE.txt
